LICENSE
MANIFEST.in
README.md
setup.cfg
setup.py
tap_bigcommerce/__init__.py
tap_bigcommerce/bigcommerce.py
tap_bigcommerce/client.py
tap_bigcommerce/discover.py
tap_bigcommerce/streams.py
tap_bigcommerce/sync.py
tap_bigcommerce/utilities.py
tap_bigcommerce.egg-info/PKG-INFO
tap_bigcommerce.egg-info/SOURCES.txt
tap_bigcommerce.egg-info/dependency_links.txt
tap_bigcommerce.egg-info/entry_points.txt
tap_bigcommerce.egg-info/requires.txt
tap_bigcommerce.egg-info/top_level.txt
tap_bigcommerce/schemas/attributevalues.json
tap_bigcommerce/schemas/coupons.json
tap_bigcommerce/schemas/customers.json
tap_bigcommerce/schemas/customersv3.json
tap_bigcommerce/schemas/orders.json
tap_bigcommerce/schemas/products.json
tap_bigcommerce/schemas/shared/type-boolean.json
tap_bigcommerce/schemas/shared/type-datetime.json
tap_bigcommerce/schemas/shared/type-integer.json
tap_bigcommerce/schemas/shared/type-number.json
tap_bigcommerce/schemas/shared/type-string.json