Metadata-Version: 2.1
Name: tap-bigcommerce
Version: 1.1.0
Summary: Sync data from your BigCommerce Store
Home-page: https://github.com/chrisgoddard
Author: Chris Goddard
License: UNKNOWN
Platform: UNKNOWN
Classifier: Programming Language :: Python :: 3 :: Only
License-File: LICENSE
